grasp_agents/__init__.py
grasp_agents/cloud_llm.py
grasp_agents/costs_dict.yaml
grasp_agents/errors.py
grasp_agents/event_bus.py
grasp_agents/generics_utils.py
grasp_agents/grasp_logging.py
grasp_agents/llm.py
grasp_agents/llm_agent.py
grasp_agents/llm_agent_memory.py
grasp_agents/llm_policy_executor.py
grasp_agents/memory.py
grasp_agents/packet.py
grasp_agents/printer.py
grasp_agents/prompt_builder.py
grasp_agents/run_context.py
grasp_agents/runner.py
grasp_agents/usage_tracker.py
grasp_agents/litellm/__init__.py
grasp_agents/litellm/completion_chunk_converters.py
grasp_agents/litellm/completion_converters.py
grasp_agents/litellm/converters.py
grasp_agents/litellm/lite_llm.py
grasp_agents/litellm/message_converters.py
grasp_agents/openai/__init__.py
grasp_agents/openai/completions/__init__.py
grasp_agents/openai/completions/chunk_converters.py
grasp_agents/openai/completions/completion_converters.py
grasp_agents/openai/completions/content_converters.py
grasp_agents/openai/completions/converters.py
grasp_agents/openai/completions/message_converters.py
grasp_agents/openai/completions/openai_llm_completions.py
grasp_agents/openai/completions/tool_converters.py
grasp_agents/openai/responses/__init__.py
grasp_agents/openai/responses/chunk_converters.py
grasp_agents/openai/responses/completion_converters.py
grasp_agents/openai/responses/completion_item_converters.py
grasp_agents/openai/responses/content_converters.py
grasp_agents/openai/responses/converters.py
grasp_agents/openai/responses/message_converters.py
grasp_agents/openai/responses/openai_responses_api.py
grasp_agents/openai/responses/tool_converters.py
grasp_agents/processors/base_processor.py
grasp_agents/processors/parallel_processor.py
grasp_agents/processors/processor.py
grasp_agents/rate_limiting/__init__.py
grasp_agents/rate_limiting/rate_limiter.py
grasp_agents/rate_limiting/types.py
grasp_agents/rate_limiting/utils.py
grasp_agents/telemetry/exporters.py
grasp_agents/telemetry/phoenix.py
grasp_agents-0.6.42.dist-info/METADATA
grasp_agents-0.6.42.dist-info/WHEEL
grasp_agents-0.6.42.dist-info/licenses/LICENSE.md
grasp_agents-0.6.42.dist-info/RECORD
