Metadata-Version: 2.4
Name: grasp_agents
Version: 0.6.42
Summary: Grasp Agents Library
License-File: LICENSE.md
Requires-Python: <4,>=3.11.4
Requires-Dist: dotenv>=0.9.9
Requires-Dist: google-genai>=1.45.0
Requires-Dist: httpx<1,>=0.27.0
Requires-Dist: litellm==1.80.10
Requires-Dist: numpy<2
Requires-Dist: openai<2.9.0,>=1.68.2
Requires-Dist: opentelemetry-sdk>=1.37.0
Requires-Dist: pydantic>=2
Requires-Dist: pyyaml>=6.0.2
Requires-Dist: tenacity<9,>=8.3.0
Requires-Dist: termcolor<3,>=2.4.0
Requires-Dist: tqdm<5,>=4.66.2
Requires-Dist: traceloop-sdk>=0.47.2
Provides-Extra: observability
Requires-Dist: arize-phoenix-otel>=0.13.1; extra == 'observability'
Requires-Dist: openinference-instrumentation-litellm>=0.1.25; extra == 'observability'
Requires-Dist: openinference-instrumentation-openai>=0.1.32; extra == 'observability'
Requires-Dist: openinference-instrumentation-openllmetry>=0.1.2; extra == 'observability'
